colcon2deb/__init__.py
colcon2deb/events.py
colcon2deb/main.py
colcon2deb/ui.py
colcon2deb/helper/build-src.sh
colcon2deb/helper/build_deb.py
colcon2deb/helper/copy-src.sh
colcon2deb/helper/create-package-list.sh
colcon2deb/helper/create-rosdep-list.sh
colcon2deb/helper/entry.sh
colcon2deb/helper/events.py
colcon2deb/helper/generate-rosdep-commands.sh
colcon2deb/helper/generate_debian_dir.py
colcon2deb/helper/install-deps.sh
colcon2deb/helper/main.py
colcon2deb/helper/prepare.sh
colcon2deb/rosdeb-bloom/README.rst
colcon2deb/rosdeb-bloom/pyproject.toml
colcon2deb/rosdeb-bloom/rosdeb_bloom/__init__.py
colcon2deb/rosdeb-bloom/rosdeb_bloom/api.py
colcon2deb/rosdeb-bloom/rosdeb_bloom/config.py
colcon2deb/rosdeb-bloom/rosdeb_bloom/git.py
colcon2deb/rosdeb-bloom/rosdeb_bloom/github.py
colcon2deb/rosdeb-bloom/rosdeb_bloom/logging.py
colcon2deb/rosdeb-bloom/rosdeb_bloom/packages.py
colcon2deb/rosdeb-bloom/rosdeb_bloom/rosdistro_api.py
colcon2deb/rosdeb-bloom/rosdeb_bloom/summary.py
colcon2deb/rosdeb-bloom/rosdeb_bloom/util.py
colcon2deb/rosdeb-bloom/rosdeb_bloom/commands/__init__.py
colcon2deb/rosdeb-bloom/rosdeb_bloom/commands/export_upstream.py
colcon2deb/rosdeb-bloom/rosdeb_bloom/commands/generate.py
colcon2deb/rosdeb-bloom/rosdeb_bloom/commands/release.py
colcon2deb/rosdeb-bloom/rosdeb_bloom/commands/update.py
colcon2deb/rosdeb-bloom/rosdeb_bloom/commands/git/__init__.py
colcon2deb/rosdeb-bloom/rosdeb_bloom/commands/git/branch.py
colcon2deb/rosdeb-bloom/rosdeb_bloom/commands/git/config.py
colcon2deb/rosdeb-bloom/rosdeb_bloom/commands/git/generate.py
colcon2deb/rosdeb-bloom/rosdeb_bloom/commands/git/import_upstream.py
colcon2deb/rosdeb-bloom/rosdeb_bloom/commands/git/release.py
colcon2deb/rosdeb-bloom/rosdeb_bloom/commands/git/patch/__init__.py
colcon2deb/rosdeb-bloom/rosdeb_bloom/commands/git/patch/common.py
colcon2deb/rosdeb-bloom/rosdeb_bloom/commands/git/patch/export_cmd.py
colcon2deb/rosdeb-bloom/rosdeb_bloom/commands/git/patch/import_cmd.py
colcon2deb-0.3.3.dist-info/METADATA
colcon2deb-0.3.3.dist-info/WHEEL
colcon2deb-0.3.3.dist-info/entry_points.txt
colcon2deb-0.3.3.dist-info/RECORD
