Metadata-Version: 2.4
Name: colcon2deb
Version: 0.3.3
Summary: Build Debian packages for Autoware in isolated Docker containers
Author-email: Autoware Foundation <contact@autoware.org>
License: Apache-2.0
Requires-Python: >=3.10
Requires-Dist: pyyaml>=6.0
Requires-Dist: rich>=13.0
